emojis/__init__.py
emojis/emojis.py
emojis/db/__init__.py
emojis/db/db.py
emojis/db/generator.py
emojis/db/utils.py
emojis-0.5.1.dist-info/LICENSE
emojis-0.5.1.dist-info/METADATA
emojis-0.5.1.dist-info/WHEEL
emojis-0.5.1.dist-info/top_level.txt
emojis-0.5.1.dist-info/RECORD
