Metadata-Version: 1.2
Name: emojis
Version: 0.5.1
Summary: Emojis for Python
Home-page: https://github.com/alexandrevicenzi/emojis
Author: Alexandre Vicenzi
Author-email: pypi@alxd.me
Maintainer: Alexandre Vicenzi
Maintainer-email: pypi@alxd.me
License: MIT
Keywords: python,emoji,emojis,unicode
Platform: 
Classifier: Development Status :: 5 - Production/Stable
Classifier: Programming Language :: Python
Classifier: Programming Language :: Python :: 3
Classifier: Programming Language :: Python :: 3.4
Classifier: Programming Language :: Python :: 3.5
Classifier: Programming Language :: Python :: 3.6
Classifier: Programming Language :: Python :: 3.7
Classifier: License :: OSI Approved :: MIT License
Classifier: Operating System :: MacOS
Classifier: Operating System :: Microsoft
Classifier: Operating System :: POSIX
Classifier: Operating System :: Unix
Classifier: Topic :: Utilities
